stoplight/__init__.py
stoplight/decorators.py
stoplight/exceptions.py
stoplight/rule.py
stoplight/tests/__init__.py
stoplight/tests/test_validation.py
stoplight-1.4.1.dist-info/DESCRIPTION.rst
stoplight-1.4.1.dist-info/METADATA
stoplight-1.4.1.dist-info/RECORD
stoplight-1.4.1.dist-info/WHEEL
stoplight-1.4.1.dist-info/metadata.json
stoplight-1.4.1.dist-info/top_level.txt
