Metadata-Version: 2.0
Name: stoplight
Version: 1.4.1
Summary: Input validation framework for Python
Home-page: https://pypi.org/project/stoplight/
Author: Jamie Painter
Author-email: jamie.painter@rackspace.com
Maintainer: Benjamen Meyer
Maintainer-email: bm_witness@yahoo.com
License: Apache License 2.0
Project-URL: Source, https://github.com/painterjd/stoplight
Project-URL: Documentation, http://stoplight.readthedocs.io/en/latest/
Project-URL: Tracker, https://github.com/painterjd/stoplight/issues
Platform: OS Independent
Classifier: Development Status :: 5 - Production/Stable
Classifier: Intended Audience :: Developers
Classifier: License :: OSI Approved :: Apache Software License
Classifier: Operating System :: OS Independent
Classifier: Programming Language :: Python
Classifier: Programming Language :: Python :: 2.7
Classifier: Programming Language :: Python :: 3.3
Classifier: Programming Language :: Python :: 3.4
Classifier: Programming Language :: Python :: 3.5
Classifier: Programming Language :: Python :: 3.6
Classifier: Programming Language :: Python :: 3.7
Classifier: Topic :: Software Development :: Libraries :: Python Modules
Classifier: Topic :: Security
Requires-Dist: six
